MasteringTensorflow1XCodeNotes/README.md
MasteringTensorflow1XCodeNotes/__init__.py
MasteringTensorflow1XCodeNotes/__main__.py
MasteringTensorflow1XCodeNotes/file.epub
MasteringTensorflow1XCodeNotes/index.html
MasteringTensorflow1XCodeNotes/css/__init__.py
MasteringTensorflow1XCodeNotes/css/annotations.css
MasteringTensorflow1XCodeNotes/css/main.css
MasteringTensorflow1XCodeNotes/css/normalize.css
MasteringTensorflow1XCodeNotes/css/popup.css
MasteringTensorflow1XCodeNotes/font/__init__.py
MasteringTensorflow1XCodeNotes/font/fontello.eot
MasteringTensorflow1XCodeNotes/font/fontello.svg
MasteringTensorflow1XCodeNotes/font/fontello.ttf
MasteringTensorflow1XCodeNotes/font/fontello.woff
MasteringTensorflow1XCodeNotes/img/__init__.py
MasteringTensorflow1XCodeNotes/img/annotator-glyph-sprite.png
MasteringTensorflow1XCodeNotes/img/annotator-icon-sprite.png
MasteringTensorflow1XCodeNotes/img/apple-touch-icon.png
MasteringTensorflow1XCodeNotes/img/cancelfullscreen.png
MasteringTensorflow1XCodeNotes/img/close.png
MasteringTensorflow1XCodeNotes/img/fullscreen.png
MasteringTensorflow1XCodeNotes/img/loader.gif
MasteringTensorflow1XCodeNotes/img/menu-icon.png
MasteringTensorflow1XCodeNotes/img/save.png
MasteringTensorflow1XCodeNotes/img/saved.png
MasteringTensorflow1XCodeNotes/img/settings-s.png
MasteringTensorflow1XCodeNotes/img/settings.png
MasteringTensorflow1XCodeNotes/img/star.png
MasteringTensorflow1XCodeNotes/js/__init__.py
MasteringTensorflow1XCodeNotes/js/epub.js
MasteringTensorflow1XCodeNotes/js/epub.min.js
MasteringTensorflow1XCodeNotes/js/epub.min.map
MasteringTensorflow1XCodeNotes/js/hooks.min.js
MasteringTensorflow1XCodeNotes/js/hooks.min.map
MasteringTensorflow1XCodeNotes/js/reader.js
MasteringTensorflow1XCodeNotes/js/reader.js.map
MasteringTensorflow1XCodeNotes/js/reader.min.js
MasteringTensorflow1XCodeNotes/js/reader.min.map
MasteringTensorflow1XCodeNotes/js/hooks/__init__.py
MasteringTensorflow1XCodeNotes/js/hooks/extensions/__init__.py
mastering_tensorflow_1_x_code_notes-2024.3.4.0.dist-info/METADATA
mastering_tensorflow_1_x_code_notes-2024.3.4.0.dist-info/WHEEL
mastering_tensorflow_1_x_code_notes-2024.3.4.0.dist-info/entry_points.txt
mastering_tensorflow_1_x_code_notes-2024.3.4.0.dist-info/top_level.txt
mastering_tensorflow_1_x_code_notes-2024.3.4.0.dist-info/RECORD
